gaumis_package/__init__.py
gaumis_package/main.py
gaumis_package-0.3.dist-info/LICENSE
gaumis_package-0.3.dist-info/METADATA
gaumis_package-0.3.dist-info/WHEEL
gaumis_package-0.3.dist-info/top_level.txt
gaumis_package-0.3.dist-info/RECORD
