Metadata-Version: 2.1
Name: gaumis_package
Version: 0.3
Summary: A package for doing cool things
Home-page: https://github.com/Gaumis/gaumis_package.git
Author: Kumar Gaurav
Author-email: kumargaurav1527@gmail.com
License: UNKNOWN
Platform: UNKNOWN
Classifier: Development Status :: 3 - Alpha
Classifier: Intended Audience :: Developers
Classifier: License :: OSI Approved :: MIT License
Classifier: Programming Language :: Python :: 3
Classifier: Programming Language :: Python :: 3.6
Classifier: Programming Language :: Python :: 3.7
Classifier: Programming Language :: Python :: 3.8
Classifier: Programming Language :: Python :: 3.9
License-File: LICENSE
